{
    "MAPSettingsUsername": "mapconcierge",
    "MAPSettingsUserKey": "user_key",
    "MAPLatitude": 35.79405833333333,
    "MAPLongitude": 139.44031944444444,
    "MAPCaptureTime": "2022_04_14_13_12_51_000",
    "MAPAltitude": 44.2,
    "MAPCompassHeading": {
        "TrueHeading": 359.0,
        "MagneticHeading": 359.0
    },
    "MAPSequenceUUID": "2d3701a1-7637-4afe-9695-d9debac67d53",
    "MAPOrientation": 1,
    "MAPDeviceMake": "RICOH",
    "MAPDeviceModel": "RICOH THETA X ",
    "MAPMetaTags": {
        "strings": [
            {
                "key": "mapillary_tools_version",
                "value": "0.7.4"
            },
            {
                "key": "mapillary_uploader_version",
                "value": "2.0.6"
            }
        ]
    },
    "MAPPhotoUUID": "7d93a37f-84ef-45a3-8eb5-277027a3f620"
}